poetry/core/__init__.py
poetry/core/_vendor/fastjsonschema/LICENSE
poetry/core/_vendor/fastjsonschema/__init__.py
poetry/core/_vendor/fastjsonschema/__main__.py
poetry/core/_vendor/fastjsonschema/draft04.py
poetry/core/_vendor/fastjsonschema/draft06.py
poetry/core/_vendor/fastjsonschema/draft07.py
poetry/core/_vendor/fastjsonschema/exceptions.py
poetry/core/_vendor/fastjsonschema/generator.py
poetry/core/_vendor/fastjsonschema/indent.py
poetry/core/_vendor/fastjsonschema/ref_resolver.py
poetry/core/_vendor/fastjsonschema/version.py
poetry/core/_vendor/lark/LICENSE
poetry/core/_vendor/lark/__init__.py
poetry/core/_vendor/lark/__pyinstaller/__init__.py
poetry/core/_vendor/lark/__pyinstaller/hook-lark.py
poetry/core/_vendor/lark/ast_utils.py
poetry/core/_vendor/lark/common.py
poetry/core/_vendor/lark/exceptions.py
poetry/core/_vendor/lark/grammar.py
poetry/core/_vendor/lark/grammars/__init__.py
poetry/core/_vendor/lark/grammars/common.lark
poetry/core/_vendor/lark/grammars/lark.lark
poetry/core/_vendor/lark/grammars/python.lark
poetry/core/_vendor/lark/grammars/unicode.lark
poetry/core/_vendor/lark/indenter.py
poetry/core/_vendor/lark/lark.py
poetry/core/_vendor/lark/lexer.py
poetry/core/_vendor/lark/load_grammar.py
poetry/core/_vendor/lark/parse_tree_builder.py
poetry/core/_vendor/lark/parser_frontends.py
poetry/core/_vendor/lark/parsers/__init__.py
poetry/core/_vendor/lark/parsers/cyk.py
poetry/core/_vendor/lark/parsers/earley.py
poetry/core/_vendor/lark/parsers/earley_common.py
poetry/core/_vendor/lark/parsers/earley_forest.py
poetry/core/_vendor/lark/parsers/grammar_analysis.py
poetry/core/_vendor/lark/parsers/lalr_analysis.py
poetry/core/_vendor/lark/parsers/lalr_interactive_parser.py
poetry/core/_vendor/lark/parsers/lalr_parser.py
poetry/core/_vendor/lark/parsers/lalr_parser_state.py
poetry/core/_vendor/lark/parsers/xearley.py
poetry/core/_vendor/lark/py.typed
poetry/core/_vendor/lark/reconstruct.py
poetry/core/_vendor/lark/tools/__init__.py
poetry_core-1.8.0.dist-info/LICENSE
poetry_core-1.8.0.dist-info/METADATA
poetry_core-1.8.0.dist-info/WHEEL
poetry_core-1.8.0.dist-info/RECORD
